{
	"archive" : {},
	"artifacts" : 
	[
		{
			"path" : "libnam_core.a"
		}
	],
	"backtrace" : 1,
	"backtraceGraph" : 
	{
		"commands" : 
		[
			"add_library",
			"target_compile_options",
			"target_compile_definitions",
			"target_include_directories"
		],
		"files" : 
		[
			"CMakeLists.txt"
		],
		"nodes" : 
		[
			{
				"file" : 0
			},
			{
				"command" : 0,
				"file" : 0,
				"line" : 32,
				"parent" : 0
			},
			{
				"command" : 1,
				"file" : 0,
				"line" : 37,
				"parent" : 0
			},
			{
				"command" : 2,
				"file" : 0,
				"line" : 33,
				"parent" : 0
			},
			{
				"command" : 3,
				"file" : 0,
				"line" : 40,
				"parent" : 0
			},
			{
				"command" : 3,
				"file" : 0,
				"line" : 46,
				"parent" : 0
			}
		]
	},
	"compileGroups" : 
	[
		{
			"compileCommandFragments" : 
			[
				{
					"fragment" : "-O3 -DNDEBUG -std=gnu++20"
				},
				{
					"backtrace" : 2,
					"fragment" : "-O3"
				},
				{
					"backtrace" : 2,
					"fragment" : "-march=native"
				},
				{
					"backtrace" : 2,
					"fragment" : "-mtune=native"
				}
			],
			"defines" : 
			[
				{
					"backtrace" : 3,
					"define" : "NAM_SAMPLE_FLOAT"
				}
			],
			"includes" : 
			[
				{
					"backtrace" : 4,
					"path" : "/home/pedal/dsp-engine-v1/third_party/NeuralAmpModelerCore/NAM"
				},
				{
					"backtrace" : 4,
					"path" : "/home/pedal/dsp-engine-v1/third_party/NeuralAmpModelerCore/Dependencies/nlohmann"
				},
				{
					"backtrace" : 5,
					"path" : "/usr/include/eigen3"
				}
			],
			"language" : "CXX",
			"languageStandard" : 
			{
				"backtraces" : 
				[
					1
				],
				"standard" : "20"
			},
			"sourceIndexes" : 
			[
				0,
				1,
				2,
				3,
				4,
				5,
				6
			]
		}
	],
	"id" : "nam_core::@6890427a1f51a3e7e1df",
	"name" : "nam_core",
	"nameOnDisk" : "libnam_core.a",
	"paths" : 
	{
		"build" : ".",
		"source" : "."
	},
	"sourceGroups" : 
	[
		{
			"name" : "Source Files",
			"sourceIndexes" : 
			[
				0,
				1,
				2,
				3,
				4,
				5,
				6
			]
		}
	],
	"sources" : 
	[
		{
			"backtrace" : 1,
			"compileGroupIndex" : 0,
			"path" : "third_party/NeuralAmpModelerCore/NAM/activations.cpp",
			"sourceGroupIndex" : 0
		},
		{
			"backtrace" : 1,
			"compileGroupIndex" : 0,
			"path" : "third_party/NeuralAmpModelerCore/NAM/convnet.cpp",
			"sourceGroupIndex" : 0
		},
		{
			"backtrace" : 1,
			"compileGroupIndex" : 0,
			"path" : "third_party/NeuralAmpModelerCore/NAM/dsp.cpp",
			"sourceGroupIndex" : 0
		},
		{
			"backtrace" : 1,
			"compileGroupIndex" : 0,
			"path" : "third_party/NeuralAmpModelerCore/NAM/get_dsp.cpp",
			"sourceGroupIndex" : 0
		},
		{
			"backtrace" : 1,
			"compileGroupIndex" : 0,
			"path" : "third_party/NeuralAmpModelerCore/NAM/lstm.cpp",
			"sourceGroupIndex" : 0
		},
		{
			"backtrace" : 1,
			"compileGroupIndex" : 0,
			"path" : "third_party/NeuralAmpModelerCore/NAM/util.cpp",
			"sourceGroupIndex" : 0
		},
		{
			"backtrace" : 1,
			"compileGroupIndex" : 0,
			"path" : "third_party/NeuralAmpModelerCore/NAM/wavenet.cpp",
			"sourceGroupIndex" : 0
		}
	],
	"type" : "STATIC_LIBRARY"
}
